setup.py
cable_modem_stats/__init__.py
cable_modem_stats/utils.py
cable_modem_stats.egg-info/PKG-INFO
cable_modem_stats.egg-info/SOURCES.txt
cable_modem_stats.egg-info/dependency_links.txt
cable_modem_stats.egg-info/requires.txt
cable_modem_stats.egg-info/top_level.txt
cable_modem_stats/models/__init__.py
cable_modem_stats/models/arris.py
cable_modem_stats/models/base.py
cable_modem_stats/stats/__init__.py
cable_modem_stats/stats/streams.py
scripts/modem-stats.py