Metadata-Version: 1.1
Name: cable-modem-stats
Version: 0.1
Summary: Pull stats from compatible cable modem's web interfaces to monitor SNR, Power, etc.
Home-page: https://bitbucket.org/phistrom/cable_modem_stats
Author: Phillip Stromberg
Author-email: phillip+cable_modem_stats@stromberg.me
License: Apache 2.0
Platform: UNKNOWN
Classifier: Development Status :: 4 - Beta
Classifier: Intended Audience :: Developers
Classifier: Intended Audience :: System Administrators
Classifier: Intended Audience :: Telecommunications Industry
Classifier: Natural Language :: English
Classifier: License :: OSI Approved :: Apache Software License
Classifier: Programming Language :: Python
Classifier: Programming Language :: Python :: 2.6
Classifier: Programming Language :: Python :: 2.7
Classifier: Programming Language :: Python :: 3
Classifier: Programming Language :: Python :: 3.3
Classifier: Programming Language :: Python :: 3.4
Classifier: Programming Language :: Python :: 3.5
Classifier: Programming Language :: Python :: Implementation :: CPython
Classifier: Topic :: System :: Networking :: Monitoring
